{"stats":{"minecraft:picked_up":{"minecraft:salmon":1,"minecraft:map":5,"minecraft:dirt":1,"minecraft:string":4,"minecraft:paper":5,"minecraft:wheat_seeds":1,"minecraft:written_book":142,"minecraft:poppy":3,"minecraft:powered_rail":1,"minecraft:torch":3,"minecraft:dandelion":2,"minecraft:oak_pressure_plate":1,"minecraft:crimson_button":1,"minecraft:ink_sac":1,"minecraft:warped_button":2,"minecraft:rail":1,"minecraft:cobblestone":16},"minecraft:used":{"minecraft:oak_trapdoor":1,"minecraft:petrified_oak_slab":2,"minecraft:nether_brick_wall":54,"minecraft:warped_fungus_on_a_stick":2,"minecraft:lodestone":2,"minecraft:flint_and_steel":2,"minecraft:soul_fire_torch":10,"minecraft:powered_rail":53,"minecraft:ladder":5,"minecraft:oak_planks":12,"minecraft:chest":30,"minecraft:bell":4,"minecraft:dried_kelp_block":54,"minecraft:salmon":1,"minecraft:diamond_block":16,"minecraft:purpur_stairs":2,"minecraft:rail":12,"minecraft:tnt":3,"minecraft:red_bed":1,"minecraft:crimson_trapdoor":4,"minecraft:prismarine_bricks":612,"minecraft:twisting_vines":2,"minecraft:prismarine_brick_stairs":29,"minecraft:warped_door":3,"minecraft:cod_bucket":6,"minecraft:shulker_box":2,"minecraft:black_bed":1,"minecraft:acacia_button":3,"minecraft:salmon_bucket":5,"minecraft:blue_concrete":1,"minecraft:redstone_torch":7,"minecraft:glass":24,"minecraft:crimson_button":2,"minecraft:lever":2,"minecraft:warped_trapdoor":7,"minecraft:bookshelf":3,"minecraft:book_box":18,"minecraft:iron_block":4,"minecraft:barrier":169,"minecraft:iron_door":2,"minecraft:wooden_sword":54,"minecraft:fishing_rod":43,"minecraft:glowstone":3,"minecraft:red_stained_glass_pane":34,"minecraft:warped_stairs":16,"minecraft:written_book":13,"minecraft:crimson_stairs":10,"minecraft:crimson_door":4,"minecraft:smooth_stone_slab":5,"minecraft:warped_button":2,"minecraft:observer":1},"minecraft:killed":{"minecraft:cat":2,"minecraft:salmon":1,"minecraft:villager":3},"minecraft:custom":{"minecraft:mob_kills":6,"minecraft:interact_with_cartography_table":3,"minecraft:open_barrel":3,"minecraft:play_one_minute":110141,"minecraft:open_shulker_box":2,"minecraft:bell_ring":127,"minecraft:interact_with_stonecutter":1,"minecraft:leave_game":1,"minecraft:time_since_death":110141,"minecraft:sleep_in_bed":3,"minecraft:climb_one_cm":2460,"minecraft:time_since_rest":50052,"minecraft:sprint_one_cm":141041,"minecraft:walk_one_cm":97518,"minecraft:drop":2,"minecraft:damage_dealt":959,"minecraft:swim_one_cm":9355,"minecraft:talked_to_villager":2,"minecraft:fly_one_cm":265950,"minecraft:open_chest":18,"minecraft:sneak_time":97,"minecraft:walk_under_water_one_cm":12316,"minecraft:jump":803,"minecraft:walk_on_water_one_cm":6238},"minecraft:dropped":{"minecraft:warped_button":1,"minecraft:written_book":1}},"DataVersion":2522}